handright/__init__.py
handright/_core.py
handright/_exceptions.py
handright/_template.py
handright/_util.py
handrightbeta-8.7.0.dist-info/LICENSE.txt
handrightbeta-8.7.0.dist-info/METADATA
handrightbeta-8.7.0.dist-info/WHEEL
handrightbeta-8.7.0.dist-info/top_level.txt
handrightbeta-8.7.0.dist-info/zip-safe
handrightbeta-8.7.0.dist-info/RECORD
