Metadata-Version: 2.1
Name: handrightbeta
Version: 8.7.0
Summary: A lightweight Python library for simulating Chinese handwriting
Home-page: https://github.com/14790897/Handright
Author: Chenghui Li (Gsllchb)
Author-email: 14790897abc@gmail.com
License: bsd-3-clause
Keywords: simulating Chinese handwriting
Classifier: Programming Language :: Python :: 3.8
Classifier: Programming Language :: Python :: 3.9
Classifier: Programming Language :: Python :: 3.10
Classifier: Programming Language :: Python :: 3.11
Classifier: Programming Language :: Python :: Implementation :: CPython
Requires-Python: >= 3.8
License-File: LICENSE.txt
Requires-Dist: pillow <11,>=8.3.2
